LbAPCommon/__init__.py
LbAPCommon/__main__.py
LbAPCommon/cern_sso.py
LbAPCommon/config.py
LbAPCommon/dirac_conversion.py
LbAPCommon/hacks.py
LbAPCommon/parsing.py
LbAPCommon/workflow.py
LbAPCommon/data/__init__.py
LbAPCommon/data/ap_merger.py
LbAPCommon/data/query_dirac.py
LbAPCommon/data/templates/configure-legacy-application.py.j2
LbAPCommon/linting/__init__.py
LbAPCommon/linting/bk_paths.py
LbAPCommon/models/__init__.py
LbAPCommon/models/recipes.py
LbAPCommon/models/validators.py
LbAPCommon/options_parsing/__init__.py
LbAPCommon/options_parsing/gaudi_pickle_to_json.py
LbAPCommon/prod_request_to_cwl/__init__.py
LbAPCommon/prod_request_to_cwl/__main__.py
LbAPCommon/prod_request_to_cwl/anaprod.py
LbAPCommon/prod_request_to_cwl/common.py
LbAPCommon/prod_request_to_cwl/simulation.py
LbAPCommon/validators/__init__.py
LbAPCommon/validators/bookkeeping_xml.py
LbAPCommon/validators/counters.py
LbAPCommon/validators/logs/__init__.py
LbAPCommon/validators/logs/data/known_messages.yaml
lbapcommon-0.14.29.dist-info/licenses/LICENSE
lbapcommon-0.14.29.dist-info/METADATA
lbapcommon-0.14.29.dist-info/WHEEL
lbapcommon-0.14.29.dist-info/entry_points.txt
lbapcommon-0.14.29.dist-info/top_level.txt
lbapcommon-0.14.29.dist-info/RECORD
